arcane/secretmanager/__init__.py
arcane/secretmanager/client.py
arcane_secretmanager-0.1.0.dist-info/METADATA
arcane_secretmanager-0.1.0.dist-info/WHEEL
arcane_secretmanager-0.1.0.dist-info/RECORD
