Metadata-Version: 2.3
Name: arcane-secretmanager
Version: 0.1.0
Summary: Client Google Cloud Secret Manager
Author: Arcane
Author-email: product@wearcane.com
Requires-Python: >=3.11,<4.0
Classifier: Programming Language :: Python :: 3
Classifier: Programming Language :: Python :: 3.11
Classifier: Programming Language :: Python :: 3.12
Classifier: Programming Language :: Python :: 3.13
Requires-Dist: google-auth (>=2.17.0,<3.0.0)
Requires-Dist: google-cloud-secret-manager (>=2.16.0,<3.0.0)
